{
	"name": "Copy_LEGO_HTTP_AzDLakeS",
	"properties": {
		"activities": [
			{
				"name": "Copy_yzi",
				"type": "Copy",
				"dependsOn": [],
				"policy": {
					"timeout": "7.00:00:00",
					"retry": 0,
					"retryIntervalInSeconds": 30,
					"secureOutput": false,
					"secureInput": false
				},
				"userProperties": [
					{
						"name": "Source",
						"value": "themes.csv.gz"
					},
					{
						"name": "Destination",
						"value": "lego//themes.parquet"
					}
				],
				"typeProperties": {
					"source": {
						"type": "DelimitedTextSource",
						"storeSettings": {
							"type": "HttpReadSettings",
							"requestMethod": "GET"
						},
						"formatSettings": {
							"type": "DelimitedTextReadSettings",
							"skipLineCount": 0
						}
					},
					"sink": {
						"type": "ParquetSink",
						"storeSettings": {
							"type": "AzureBlobFSWriteSettings"
						},
						"formatSettings": {
							"type": "ParquetWriteSettings"
						}
					},
					"enableStaging": false,
					"enableSkipIncompatibleRow": true,
					"logSettings": {
						"enableCopyActivityLog": true,
						"copyActivityLogSettings": {
							"logLevel": "Warning",
							"enableReliableLogging": false
						},
						"logLocationSettings": {
							"linkedServiceName": {
								"referenceName": "AzDLake_Lego_Storage",
								"type": "LinkedServiceReference"
							},
							"path": "lego/errors/themes"
						}
					}
				},
				"inputs": [
					{
						"referenceName": "Source_HTTP_LegoBricks",
						"type": "DatasetReference"
					}
				],
				"outputs": [
					{
						"referenceName": "Destination_Lego_DS",
						"type": "DatasetReference"
					}
				]
			}
		],
		"annotations": [],
		"lastPublishTime": "2022-03-23T11:25:17Z"
	},
	"type": "Microsoft.DataFactory/factories/pipelines"
}